{
  "1": {
    "inputs": {
      "ckpt_name": "v1-5-pruned-emaonly.safetensors"
    },
    "class_type": "CheckpointLoaderSimple",
    "_meta": {
      "title": "Load Checkpoint"
    }
  },
  "2": {
    "inputs": {
      "text": "masterpiece, best quality, cinematic, detailed face, soft lighting",
      "clip": ["1", 1]
    },
    "class_type": "CLIPTextEncode",
    "_meta": {
      "title": "CLIP Text Encode (Positive)"
    }
  },
  "3": {
    "inputs": {
      "text": "blurry, distorted, low quality, bad anatomy, static",
      "clip": ["1", 1]
    },
    "class_type": "CLIPTextEncode",
    "_meta": {
      "title": "CLIP Text Encode (Negative)"
    }
  },
  "4": {
    "inputs": {
      "seed": 42,
      "steps": 15,
      "cfg": 7.5,
      "sampler_name": "dpmpp_2m",
      "scheduler": "karras",
      "denoise": 1.0,
      "model": ["1", 0],
      "positive": ["2", 0],
      "negative": ["3", 0],
      "latent_image": ["5", 0]
    },
    "class_type": "KSampler",
    "_meta": {
      "title": "KSampler"
    }
  },
  "5": {
    "inputs": {
      "width": 512,
      "height": 512,
      "batch_size": 1
    },
    "class_type": "EmptyLatentImage",
    "_meta": {
      "title": "Empty Latent Image"
    }
  },
  "6": {
    "inputs": {
      "samples": ["4", 0],
      "vae": ["1", 2]
    },
    "class_type": "VAEDecode",
    "_meta": {
      "title": "VAE Decode"
    }
  },
  "7": {
    "inputs": {
      "images": ["6", 0],
      "filename_prefix": "sd15_test"
    },
    "class_type": "SaveImage",
    "_meta": {
      "title": "Save Image"
    }
  }
}
